LICENSE
pynoticenter/__init__.py
pynoticenter/noticenter.py
pynoticenter/noticenter_observer.py
pynoticenter/options.py
pynoticenter/task.py
pynoticenter/task_queue.py
pynoticenter/utils.py
pynoticenter-0.1.11.dist-info/entry_points.txt
pynoticenter-0.1.11.dist-info/LICENSE
pynoticenter-0.1.11.dist-info/WHEEL
pynoticenter-0.1.11.dist-info/METADATA
pynoticenter-0.1.11.dist-info/RECORD
