Metadata-Version: 2.1
Name: pynoticenter
Version: 0.1.11
Summary: Python client side notification center.
Home-page: https://github.com/dzhsurf/pynoticenter
License: MIT
Keywords: post task,task queue,notification,notification center
Author: dzhsurf
Author-email: dzhsurf@gmail.com
Requires-Python: >=3.9,<4.0
Classifier: License :: OSI Approved :: MIT License
Classifier: Programming Language :: Python :: 3
Classifier: Programming Language :: Python :: 3.9
Classifier: Programming Language :: Python :: 3.10
Classifier: Programming Language :: Python :: 3.11
Requires-Dist: asyncio (>=3.4.3,<4.0.0)
Project-URL: Repository, https://github.com/dzhsurf/pynoticenter
